HisarCSPiWars2019/Controller.py
HisarCSPiWars2019/MotorControl.py
HisarCSPiWars2019/OptimizedPiCam.py
HisarCSPiWars2019/ServoControl.py
HisarCSPiWars2019/UltrasonicSensor.py
HisarCSPiWars2019/__init__.py
HisarCSPiwars2019-0.9.5.dist-info/METADATA
HisarCSPiwars2019-0.9.5.dist-info/WHEEL
HisarCSPiwars2019-0.9.5.dist-info/top_level.txt
HisarCSPiwars2019-0.9.5.dist-info/RECORD
