Metadata-Version: 2.1
Name: HisarCSPiwars2019
Version: 0.9.5
Summary: Library that makes use of sensors, motors, and servos made for the  PiWars competition by HisarCS
Home-page: UNKNOWN
Author: Yaşar İdikut, Sarp Yoel Kastro
Author-email: yasar.idikut@hisarschool.k12.tr, sarp.kastro@hisarschool.k12.tr
License: UNKNOWN
Platform: UNKNOWN
Classifier: Development Status :: 4 - Beta
